avonage/__init__.py
avonage/client.py
avonage-0.1.2.dist-info/METADATA
avonage-0.1.2.dist-info/WHEEL
avonage-0.1.2.dist-info/top_level.txt
avonage-0.1.2.dist-info/RECORD
