Metadata-Version: 2.1
Name: avonage
Version: 0.1.2
Summary: Asynchronous Vonage / Nexmo client
Home-page: https://github.com/adyachok/avonage
Author: Andras Gyacsok
Author-email: atti.dyachok@gmail.com
License: MIT
Platform: UNKNOWN
Requires-Dist: aiohttp
